MANIFEST.in
README.md
setup.cfg
setup.py
liuxuebo_pypi_demo.egg-info/PKG-INFO
liuxuebo_pypi_demo.egg-info/SOURCES.txt
liuxuebo_pypi_demo.egg-info/dependency_links.txt
liuxuebo_pypi_demo.egg-info/top_level.txt
pypi_demo/__init__.py
pypi_demo/pypi_demo.py