Metadata-Version: 1.0
Name: liuxuebo-pypi-demo
Version: 1.0
Summary: a library for learning pypi
Home-page: UNKNOWN
Author: liuxuebo
Author-email: lufo816@gmail.com
License: MIT License
Keywords: demo
Platform: any
